{
 "actions": [],
 "allow_rename": 1,
 "creation": "2024-05-30 19:18:29.479456",
 "doctype": "DocType",
 "editable_grid": 1,
 "engine": "InnoDB",
 "field_order": [
  "warranty_records_section",
  "amc_id",
  "start_date",
  "end_date",
  "service_count",
  "period_of_month",
  "contract_date",
  "serviced_by",
  "enrolment"
 ],
 "fields": [
  {
   "fieldname": "warranty_records_section",
   "fieldtype": "Section Break"
  },
  {
   "fieldname": "start_date",
   "fieldtype": "Date",
   "in_list_view": 1,
   "label": "Start Date",
   "read_only": 1
  },
  {
   "fieldname": "end_date",
   "fieldtype": "Date",
   "in_list_view": 1,
   "label": "End date",
   "read_only": 1
  },
  {
   "fieldname": "service_count",
   "fieldtype": "Data",
   "in_list_view": 1,
   "label": "Service Count",
   "read_only": 1
  },
  {
   "fieldname": "period_of_month",
   "fieldtype": "Data",
   "in_list_view": 1,
   "label": "Period of Month",
   "read_only": 1
  },
  {
   "fieldname": "contract_date",
   "fieldtype": "Date",
   "in_list_view": 1,
   "label": "Contract Date",
   "read_only": 1
  },
  {
   "fieldname": "serviced_by",
   "fieldtype": "Data",
   "in_list_view": 1,
   "label": "Serviced By",
   "read_only": 1
  },
  {
   "fieldname": "enrolment",
   "fieldtype": "Data",
   "in_list_view": 1,
   "label": "Enrolment",
   "read_only": 1
  },
  {
   "fieldname": "amc_id",
   "fieldtype": "Link",
   "in_list_view": 1,
   "label": "AMC ID",
   "options": "AMC",
   "read_only": 1
  }
 ],
 "index_web_pages_for_search": 1,
 "istable": 1,
 "links": [],
 "modified": "2024-06-26 15:24:27.903683",
 "modified_by": "Administrator",
 "module": "pie-sol",
 "name": "AMC records",
 "owner": "Administrator",
 "permissions": [],
 "sort_field": "modified",
 "sort_order": "DESC",
 "states": []
}